smallsmt_openpnp_server/__init__.py
smallsmt_openpnp_server/__main__.py
smallsmt_openpnp_server/aboutdialog.py
smallsmt_openpnp_server/commserial.py
smallsmt_openpnp_server/commsockets.py
smallsmt_openpnp_server/configtreeview.py
smallsmt_openpnp_server/dialogplayground.py
smallsmt_openpnp_server/editconfig.py
smallsmt_openpnp_server/machineconfig.py
smallsmt_openpnp_server/mainwindow.py
smallsmt_openpnp_server/openpnp.py
smallsmt_openpnp_server/openpnpcoords.py
smallsmt_openpnp_server/openpnpmessanger.py
smallsmt_openpnp_server/smallsmt_openpnp_server.py
smallsmt_openpnp_server/smallsmtconfig.py
smallsmt_openpnp_server/smallsmtmessanger.py
smallsmt_openpnp_server/smallsmtprotocol.py
smallsmt_openpnp_server/test.py
smallsmt_openpnp_server-1.10.dist-info/LICENSE
smallsmt_openpnp_server-1.10.dist-info/METADATA
smallsmt_openpnp_server-1.10.dist-info/WHEEL
smallsmt_openpnp_server-1.10.dist-info/top_level.txt
smallsmt_openpnp_server-1.10.dist-info/RECORD
