Metadata-Version: 2.1
Name: smallsmt-openpnp-server
Version: 1.10
Summary: Python server for SmallSmt Pick&Place machines
Home-page: http://www.kartech.org
Author: Jaroslaw Karwik
Author-email: jaroslaw.karwik@gmail.com
License: MIT
Platform: UNKNOWN
Classifier: Development Status :: 3 - Alpha
Classifier: Topic :: Utilities
Classifier: License :: OSI Approved :: MIT License
Classifier: Programming Language :: Python :: 3.6
Requires-Dist: pyqt5
Requires-Dist: jsonpickle
